gotossh/__init__.py
gotossh/bin/gotossh
gotossh-0.0.1.dist-info/DESCRIPTION.rst
gotossh-0.0.1.dist-info/METADATA
gotossh-0.0.1.dist-info/RECORD
gotossh-0.0.1.dist-info/WHEEL
gotossh-0.0.1.dist-info/entry_points.txt
gotossh-0.0.1.dist-info/metadata.json
gotossh-0.0.1.dist-info/top_level.txt
