Metadata-Version: 2.0
Name: gotossh
Version: 0.0.1
Summary: jump to ssh server quickly
Home-page: http://github.com/CuberL/goto
Author: cuberl
Author-email: me@cuberl.com
License: MIT License
Keywords: quick,goto,ssh
Platform: any
Requires-Dist: argcomplete
